semiautomatic/__init__.py
semiautomatic/cli.py
semiautomatic/defaults.py
semiautomatic/image/__init__.py
semiautomatic/image/generate.py
semiautomatic/image/process.py
semiautomatic/image/upscale.py
semiautomatic/image/providers/__init__.py
semiautomatic/image/providers/base.py
semiautomatic/image/providers/fal.py
semiautomatic/image/providers/fal_models.py
semiautomatic/image/providers/freepik.py
semiautomatic/image/providers/recraft.py
semiautomatic/image/providers/recraft_styles.py
semiautomatic/lib/__init__.py
semiautomatic/lib/api.py
semiautomatic/lib/env.py
semiautomatic/lib/logging.py
semiautomatic/lib/s3.py
semiautomatic/lib/storage.py
semiautomatic/lib/subprocess.py
semiautomatic/lib/llm/__init__.py
semiautomatic/lib/llm/base.py
semiautomatic/lib/llm/claude.py
semiautomatic/lib/llm/openai.py
semiautomatic/lib/vision/__init__.py
semiautomatic/lib/vision/base.py
semiautomatic/lib/vision/huggingface.py
semiautomatic/lib/vision/moondream.py
semiautomatic/prompt/__init__.py
semiautomatic/prompt/image.py
semiautomatic/prompt/models.py
semiautomatic/prompt/video.py
semiautomatic/video/__init__.py
semiautomatic/video/easing.py
semiautomatic/video/ffmpeg.py
semiautomatic/video/frames.py
semiautomatic/video/generate.py
semiautomatic/video/info.py
semiautomatic/video/process.py
semiautomatic/video/providers/__init__.py
semiautomatic/video/providers/base.py
semiautomatic/video/providers/fal.py
semiautomatic/video/providers/fal_models.py
semiautomatic/video/providers/higgsfield.py
semiautomatic/video/providers/motions.py
semiautomatic/video/providers/wavespeed.py
semiautomatic-0.2.1b1.dist-info/METADATA
semiautomatic-0.2.1b1.dist-info/WHEEL
semiautomatic-0.2.1b1.dist-info/entry_points.txt
semiautomatic-0.2.1b1.dist-info/licenses/LICENSE
semiautomatic-0.2.1b1.dist-info/RECORD
