Metadata-Version: 2.4
Name: semiautomatic
Version: 0.2.1b1
Summary: AI automation tools for creative workflows
Project-URL: Homepage, https://github.com/drpolygon/semiautomatic
Project-URL: Repository, https://github.com/drpolygon/semiautomatic
Author-email: Daryl Anselmo <daryl@darylanselmo.com>
License-Expression: MIT
License-File: LICENSE
Requires-Python: >=3.9
Requires-Dist: fal-client>=0.5.0
Requires-Dist: pillow>=9.0.0
Requires-Dist: python-dotenv>=1.0.0
Requires-Dist: requests>=2.31.0
